{"packages":{"skeeks/cms-marketplace":{"1.0.0":{"name":"skeeks/cms-marketplace","description":"Marketplace for SkeekS CMS","keywords":["framework","component","yii","marketplace","skeeks"],"homepage":"http://cms.skeeks.com/","version":"1.0.0","version_normalized":"1.0.0.0","license":["GPL-3.0+"],"authors":[{"name":"Semenov Alexander","email":"semenov@skeeks.com"}],"source":{"type":"git","url":"https://github.com/skeeks-cms/cms-marketplace.git","reference":"12bd593a33aa19ba6310f964a341fc3204dfc31d"},"dist":{"type":"zip","url":"https://api.github.com/repos/skeeks-cms/cms-marketplace/zipball/12bd593a33aa19ba6310f964a341fc3204dfc31d","reference":"12bd593a33aa19ba6310f964a341fc3204dfc31d","shasum":""},"type":"yii2-extension","time":"2016-05-28T13:33:57+00:00","autoload":{"psr-4":{"skeeks\\cms\\marketplace\\":""}},"require":{"skeeks/cms":"*","skeeks/yii2-curl":"*"},"uid":839799},"1.0.0-alpha":{"name":"skeeks/cms-marketplace","description":"Marketplace for SkeekS CMS","keywords":["framework","component","yii","marketplace","skeeks"],"homepage":"http://cms.skeeks.com/","version":"1.0.0-alpha","version_normalized":"1.0.0.0-alpha","license":["GPL-3.0+"],"authors":[{"name":"Semenov Alexander","email":"semenov@skeeks.com"}],"source":{"type":"git","url":"https://github.com/skeeks-cms/cms-marketplace.git","reference":"a77dc178e6058e7a13123fbed175907b0873fdb1"},"dist":{"type":"zip","url":"https://api.github.com/repos/skeeks-cms/cms-marketplace/zipball/a77dc178e6058e7a13123fbed175907b0873fdb1","reference":"a77dc178e6058e7a13123fbed175907b0873fdb1","shasum":""},"type":"yii2-extension","time":"2016-04-19T21:25:27+00:00","autoload":{"psr-4":{"skeeks\\cms\\marketplace\\":""}},"require":{"skeeks/cms":"*","skeeks/yii2-curl":"*"},"uid":787251},"1.0.1":{"name":"skeeks/cms-marketplace","description":"Marketplace for SkeekS CMS","keywords":["framework","component","yii","marketplace","skeeks"],"homepage":"http://cms.skeeks.com/","version":"1.0.1","version_normalized":"1.0.1.0","license":["GPL-3.0+"],"authors":[{"name":"Semenov Alexander","email":"semenov@skeeks.com"}],"source":{"type":"git","url":"https://github.com/skeeks-cms/cms-marketplace.git","reference":"800b9c848c1752bb1730d1eb62b0d7c3bc5895fc"},"dist":{"type":"zip","url":"https://api.github.com/repos/skeeks-cms/cms-marketplace/zipball/800b9c848c1752bb1730d1eb62b0d7c3bc5895fc","reference":"800b9c848c1752bb1730d1eb62b0d7c3bc5895fc","shasum":""},"type":"yii2-extension","time":"2016-07-15T13:42:45+00:00","autoload":{"psr-4":{"skeeks\\cms\\marketplace\\":""}},"require":{"skeeks/cms":"*","skeeks/yii2-curl":"*"},"uid":903872},"1.0.2":{"name":"skeeks/cms-marketplace","description":"Marketplace for SkeekS CMS","keywords":["framework","component","yii","marketplace","skeeks"],"homepage":"http://cms.skeeks.com/","version":"1.0.2","version_normalized":"1.0.2.0","license":["GPL-3.0+"],"authors":[{"name":"Semenov Alexander","email":"semenov@skeeks.com"}],"source":{"type":"git","url":"https://github.com/skeeks-cms/cms-marketplace.git","reference":"93b715ed533c6026b94f8d89aa7c921ba9d948f6"},"dist":{"type":"zip","url":"https://api.github.com/repos/skeeks-cms/cms-marketplace/zipball/93b715ed533c6026b94f8d89aa7c921ba9d948f6","reference":"93b715ed533c6026b94f8d89aa7c921ba9d948f6","shasum":""},"type":"yii2-extension","time":"2016-09-14T08:45:03+00:00","autoload":{"psr-4":{"skeeks\\cms\\marketplace\\":""}},"require":{"skeeks/cms":"*","skeeks/yii2-curl":"*"},"uid":992853},"1.0.3":{"name":"skeeks/cms-marketplace","description":"Marketplace for SkeekS CMS","keywords":["framework","component","yii","marketplace","skeeks"],"homepage":"http://cms.skeeks.com/","version":"1.0.3","version_normalized":"1.0.3.0","license":["GPL-3.0+"],"authors":[{"name":"Semenov Alexander","email":"semenov@skeeks.com"}],"source":{"type":"git","url":"https://github.com/skeeks-cms/cms-marketplace.git","reference":"c062536e9a03008727f32e6b375e8d2b02d3e32d"},"dist":{"type":"zip","url":"https://api.github.com/repos/skeeks-cms/cms-marketplace/zipball/c062536e9a03008727f32e6b375e8d2b02d3e32d","reference":"c062536e9a03008727f32e6b375e8d2b02d3e32d","shasum":""},"type":"yii2-extension","time":"2016-12-22T23:15:16+00:00","autoload":{"psr-4":{"skeeks\\cms\\marketplace\\":""}},"require":{"skeeks/cms":"*","skeeks/yii2-curl":"*"},"uid":1139627},"1.1.0":{"name":"skeeks/cms-marketplace","description":"Marketplace for SkeekS CMS","keywords":["framework","component","yii","marketplace","skeeks"],"homepage":"http://cms.skeeks.com/","version":"1.1.0","version_normalized":"1.1.0.0","license":["GPL-3.0+"],"authors":[{"name":"Semenov Alexander","email":"semenov@skeeks.com"}],"source":{"type":"git","url":"https://github.com/skeeks-cms/cms-marketplace.git","reference":"abc1212c19044f660380cc424f2cb4e3e91902c2"},"dist":{"type":"zip","url":"https://api.github.com/repos/skeeks-cms/cms-marketplace/zipball/abc1212c19044f660380cc424f2cb4e3e91902c2","reference":"abc1212c19044f660380cc424f2cb4e3e91902c2","shasum":""},"type":"yii2-extension","time":"2017-03-02T22:44:13+00:00","autoload":{"psr-4":{"skeeks\\cms\\marketplace\\":""}},"require":{"skeeks/cms":"*","skeeks/yii2-curl":"*"},"uid":1263802},"1.2.0":{"name":"skeeks/cms-marketplace","description":"Marketplace for SkeekS CMS","keywords":["framework","component","yii","marketplace","skeeks"],"homepage":"http://cms.skeeks.com/","version":"1.2.0","version_normalized":"1.2.0.0","license":["GPL-3.0+"],"authors":[{"name":"Semenov Alexander","email":"semenov@skeeks.com"}],"source":{"type":"git","url":"https://github.com/skeeks-cms/cms-marketplace.git","reference":"9cd9ddc19b955488a9bac6ebbb382f68043088d4"},"dist":{"type":"zip","url":"https://api.github.com/repos/skeeks-cms/cms-marketplace/zipball/9cd9ddc19b955488a9bac6ebbb382f68043088d4","reference":"9cd9ddc19b955488a9bac6ebbb382f68043088d4","shasum":""},"type":"yii2-extension","time":"2017-11-07T10:34:58+00:00","autoload":{"psr-4":{"skeeks\\cms\\marketplace\\":""}},"extra":{"config-plugin":{"web":"config/main.php","console":"config/main-console.php"}},"require":{"skeeks/cms":"*","skeeks/yii2-curl":"*"},"uid":1709757},"2.0.0":{"name":"skeeks/cms-marketplace","description":"Marketplace for SkeekS CMS","keywords":["framework","component","yii","marketplace","skeeks"],"homepage":"http://cms.skeeks.com/","version":"2.0.0","version_normalized":"2.0.0.0","license":["BSD-3-Clause"],"authors":[{"name":"Semenov Alexander","email":"semenov@skeeks.com"}],"source":{"type":"git","url":"https://github.com/skeeks-cms/cms-marketplace.git","reference":"8da4abc90359a1dd985a3f357de4ad829fd15f58"},"dist":{"type":"zip","url":"https://api.github.com/repos/skeeks-cms/cms-marketplace/zipball/8da4abc90359a1dd985a3f357de4ad829fd15f58","reference":"8da4abc90359a1dd985a3f357de4ad829fd15f58","shasum":""},"type":"yii2-extension","time":"2018-01-30T22:26:09+00:00","autoload":{"psr-4":{"skeeks\\cms\\marketplace\\":"src/"}},"extra":{"config-plugin":{"web":"src/config/web.php"}},"require":{"skeeks/cms":"~5.0.0 || dev-master","skeeks/cms-composer-update-plugin":"~1.0.0 || dev-master","symfony/process":"~3.3.6","skeeks/yii2-curl":"*"},"uid":1880724},"2.0.0-alpha":{"name":"skeeks/cms-marketplace","description":"Marketplace for SkeekS CMS","keywords":["framework","component","yii","marketplace","skeeks"],"homepage":"http://cms.skeeks.com/","version":"2.0.0-alpha","version_normalized":"2.0.0.0-alpha","license":["GPL-3.0+"],"authors":[{"name":"Semenov Alexander","email":"semenov@skeeks.com"}],"source":{"type":"git","url":"https://github.com/skeeks-cms/cms-marketplace.git","reference":"e6a73366efef536ffd43b8bb67293e16bd3926bd"},"dist":{"type":"zip","url":"https://api.github.com/repos/skeeks-cms/cms-marketplace/zipball/e6a73366efef536ffd43b8bb67293e16bd3926bd","reference":"e6a73366efef536ffd43b8bb67293e16bd3926bd","shasum":""},"type":"yii2-extension","time":"2017-11-15T10:40:40+00:00","autoload":{"psr-4":{"skeeks\\cms\\marketplace\\":"src/"}},"extra":{"config-plugin":{"web":"src/config/web.php"}},"require":{"skeeks/cms":"~5.0.0 || dev-master","symfony/process":"~3.3.12","skeeks/yii2-curl":"*"},"uid":1728359},"2.0.0-alpha2":{"name":"skeeks/cms-marketplace","description":"Marketplace for SkeekS CMS","keywords":["framework","component","yii","marketplace","skeeks"],"homepage":"http://cms.skeeks.com/","version":"2.0.0-alpha2","version_normalized":"2.0.0.0-alpha2","license":["GPL-3.0+"],"authors":[{"name":"Semenov Alexander","email":"semenov@skeeks.com"}],"source":{"type":"git","url":"https://github.com/skeeks-cms/cms-marketplace.git","reference":"137c010cca267992b04bcb6cee0dd47f492439c6"},"dist":{"type":"zip","url":"https://api.github.com/repos/skeeks-cms/cms-marketplace/zipball/137c010cca267992b04bcb6cee0dd47f492439c6","reference":"137c010cca267992b04bcb6cee0dd47f492439c6","shasum":""},"type":"yii2-extension","time":"2017-11-15T11:16:44+00:00","autoload":{"psr-4":{"skeeks\\cms\\marketplace\\":"src/"}},"extra":{"class":"skeeks\\cms\\marketplace\\composer\\UpdatePlugin","config-plugin":{"web":"src/config/web.php"}},"require":{"skeeks/cms":"~5.0.0 || dev-master","symfony/process":"~3.3.12","skeeks/yii2-curl":"*"},"uid":1728446},"2.0.0-alpha3":{"name":"skeeks/cms-marketplace","description":"Marketplace for SkeekS CMS","keywords":["framework","component","yii","marketplace","skeeks"],"homepage":"http://cms.skeeks.com/","version":"2.0.0-alpha3","version_normalized":"2.0.0.0-alpha3","license":["GPL-3.0+"],"authors":[{"name":"Semenov Alexander","email":"semenov@skeeks.com"}],"source":{"type":"git","url":"https://github.com/skeeks-cms/cms-marketplace.git","reference":"25bfc1db679df2c9e08416f9feb164088baf10c0"},"dist":{"type":"zip","url":"https://api.github.com/repos/skeeks-cms/cms-marketplace/zipball/25bfc1db679df2c9e08416f9feb164088baf10c0","reference":"25bfc1db679df2c9e08416f9feb164088baf10c0","shasum":""},"type":"yii2-extension","time":"2017-11-15T12:52:06+00:00","autoload":{"psr-4":{"skeeks\\cms\\marketplace\\":"src/"}},"extra":{"config-plugin":{"web":"src/config/web.php"}},"require":{"skeeks/cms":"~5.0.0 || dev-master","skeeks/cms-composer-update-plugin":"~1.0.0 || dev-master","symfony/process":"~3.3.12","skeeks/yii2-curl":"*"},"uid":1728668},"2.0.0-alpha4":{"name":"skeeks/cms-marketplace","description":"Marketplace for SkeekS CMS","keywords":["framework","component","yii","marketplace","skeeks"],"homepage":"http://cms.skeeks.com/","version":"2.0.0-alpha4","version_normalized":"2.0.0.0-alpha4","license":["GPL-3.0+"],"authors":[{"name":"Semenov Alexander","email":"semenov@skeeks.com"}],"source":{"type":"git","url":"https://github.com/skeeks-cms/cms-marketplace.git","reference":"d964618960e41f84635fdc44871f6b0380ca74df"},"dist":{"type":"zip","url":"https://api.github.com/repos/skeeks-cms/cms-marketplace/zipball/d964618960e41f84635fdc44871f6b0380ca74df","reference":"d964618960e41f84635fdc44871f6b0380ca74df","shasum":""},"type":"yii2-extension","time":"2017-11-15T22:08:00+00:00","autoload":{"psr-4":{"skeeks\\cms\\marketplace\\":"src/"}},"extra":{"config-plugin":{"web":"src/config/web.php"}},"require":{"skeeks/cms":"~5.0.0 || dev-master","skeeks/cms-composer-update-plugin":"~1.0.0 || dev-master","symfony/process":"~3.3.6","skeeks/yii2-curl":"*"},"uid":1729612},"2.0.1":{"name":"skeeks/cms-marketplace","description":"Marketplace for SkeekS CMS","keywords":["framework","component","yii","marketplace","skeeks"],"homepage":"http://cms.skeeks.com/","version":"2.0.1","version_normalized":"2.0.1.0","license":["BSD-3-Clause"],"authors":[{"name":"Semenov Alexander","email":"semenov@skeeks.com"}],"source":{"type":"git","url":"https://github.com/skeeks-cms/cms-marketplace.git","reference":"e0902e5e4b702fe4f4e877cc298e40a8ca413c4a"},"dist":{"type":"zip","url":"https://api.github.com/repos/skeeks-cms/cms-marketplace/zipball/e0902e5e4b702fe4f4e877cc298e40a8ca413c4a","reference":"e0902e5e4b702fe4f4e877cc298e40a8ca413c4a","shasum":""},"type":"yii2-extension","time":"2018-05-21T16:14:54+00:00","autoload":{"psr-4":{"skeeks\\cms\\marketplace\\":"src/"}},"extra":{"config-plugin":{"web":"src/config/web.php"}},"require":{"skeeks/cms":"^5.0.4 || dev-master","skeeks/cms-composer-update-plugin":"^1.0.0 || dev-master","skeeks/yii2-curl":"^1.1.0","symfony/process":"~3.3.6"},"uid":2215195},"2.0.2":{"name":"skeeks/cms-marketplace","description":"Marketplace for SkeekS CMS","keywords":["framework","component","yii","marketplace","skeeks"],"homepage":"http://cms.skeeks.com/","version":"2.0.2","version_normalized":"2.0.2.0","license":["BSD-3-Clause"],"authors":[{"name":"Semenov Alexander","email":"semenov@skeeks.com"}],"source":{"type":"git","url":"https://github.com/skeeks-cms/cms-marketplace.git","reference":"9f76e1555ec0f35faeea1dbcdce1dfb4a43b6894"},"dist":{"type":"zip","url":"https://api.github.com/repos/skeeks-cms/cms-marketplace/zipball/9f76e1555ec0f35faeea1dbcdce1dfb4a43b6894","reference":"9f76e1555ec0f35faeea1dbcdce1dfb4a43b6894","shasum":""},"type":"yii2-extension","time":"2019-01-15T16:14:09+00:00","autoload":{"psr-4":{"skeeks\\cms\\marketplace\\":"src/"}},"extra":{"config-plugin":{"web":"src/config/web.php"}},"require":{"skeeks/cms":"^5.0.4 || dev-master","skeeks/cms-composer-update-plugin":"^1.0.0 || dev-master","yiisoft/yii2-httpclient":"^2","symfony/process":"~3.3.6"},"uid":2692787},"2.0.2.1":{"name":"skeeks/cms-marketplace","description":"Marketplace for SkeekS CMS","keywords":["framework","component","yii","marketplace","skeeks"],"homepage":"http://cms.skeeks.com/","version":"2.0.2.1","version_normalized":"2.0.2.1","license":["BSD-3-Clause"],"authors":[{"name":"Semenov Alexander","email":"semenov@skeeks.com"}],"source":{"type":"git","url":"https://github.com/skeeks-cms/cms-marketplace.git","reference":"2e90763fe01179be4802890183f19d6f3ccd27df"},"dist":{"type":"zip","url":"https://api.github.com/repos/skeeks-cms/cms-marketplace/zipball/2e90763fe01179be4802890183f19d6f3ccd27df","reference":"2e90763fe01179be4802890183f19d6f3ccd27df","shasum":""},"type":"yii2-extension","time":"2019-01-26T16:23:00+00:00","autoload":{"psr-4":{"skeeks\\cms\\marketplace\\":"src/"}},"extra":{"config-plugin":{"web":["src/config/common.php","src/config/web.php"],"console":["src/config/common.php"]}},"require":{"skeeks/cms":"^5.0.4 || dev-master","skeeks/cms-composer-update-plugin":"^1.0.0 || dev-master","yiisoft/yii2-httpclient":"^2","symfony/process":"~3.3.6"},"uid":2718859},"2.0.2.2":{"name":"skeeks/cms-marketplace","description":"Marketplace for SkeekS CMS","keywords":["framework","component","yii","marketplace","skeeks"],"homepage":"http://cms.skeeks.com/","version":"2.0.2.2","version_normalized":"2.0.2.2","license":["BSD-3-Clause"],"authors":[{"name":"Semenov Alexander","email":"semenov@skeeks.com"}],"source":{"type":"git","url":"https://github.com/skeeks-cms/cms-marketplace.git","reference":"2e90763fe01179be4802890183f19d6f3ccd27df"},"dist":{"type":"zip","url":"https://api.github.com/repos/skeeks-cms/cms-marketplace/zipball/2e90763fe01179be4802890183f19d6f3ccd27df","reference":"2e90763fe01179be4802890183f19d6f3ccd27df","shasum":""},"type":"yii2-extension","time":"2019-01-26T16:23:00+00:00","autoload":{"psr-4":{"skeeks\\cms\\marketplace\\":"src/"}},"extra":{"config-plugin":{"web":["src/config/common.php","src/config/web.php"],"console":["src/config/common.php"]}},"require":{"skeeks/cms":"^5.0.4 || dev-master","skeeks/cms-composer-update-plugin":"^1.0.0 || dev-master","yiisoft/yii2-httpclient":"^2","symfony/process":"~3.3.6"},"uid":2723821},"2.0.2.3":{"name":"skeeks/cms-marketplace","description":"Marketplace for SkeekS CMS","keywords":["framework","component","yii","marketplace","skeeks"],"homepage":"http://cms.skeeks.com/","version":"2.0.2.3","version_normalized":"2.0.2.3","license":["BSD-3-Clause"],"authors":[{"name":"Semenov Alexander","email":"semenov@skeeks.com"}],"source":{"type":"git","url":"https://github.com/skeeks-cms/cms-marketplace.git","reference":"2e90763fe01179be4802890183f19d6f3ccd27df"},"dist":{"type":"zip","url":"https://api.github.com/repos/skeeks-cms/cms-marketplace/zipball/2e90763fe01179be4802890183f19d6f3ccd27df","reference":"2e90763fe01179be4802890183f19d6f3ccd27df","shasum":""},"type":"yii2-extension","time":"2019-01-26T16:23:00+00:00","autoload":{"psr-4":{"skeeks\\cms\\marketplace\\":"src/"}},"extra":{"config-plugin":{"web":["src/config/common.php","src/config/web.php"],"console":["src/config/common.php"]}},"require":{"skeeks/cms":"^5.0.4 || dev-master","skeeks/cms-composer-update-plugin":"^1.0.0 || dev-master","yiisoft/yii2-httpclient":"^2","symfony/process":"~3.3.6"},"uid":2723826},"2.0.2.4":{"name":"skeeks/cms-marketplace","description":"Marketplace for SkeekS CMS","keywords":["framework","component","yii","marketplace","skeeks"],"homepage":"http://cms.skeeks.com/","version":"2.0.2.4","version_normalized":"2.0.2.4","license":["BSD-3-Clause"],"authors":[{"name":"Semenov Alexander","email":"semenov@skeeks.com"}],"source":{"type":"git","url":"https://github.com/skeeks-cms/cms-marketplace.git","reference":"e6ae203adaeacc39c7eac8b38a8b8b4d20975cad"},"dist":{"type":"zip","url":"https://api.github.com/repos/skeeks-cms/cms-marketplace/zipball/e6ae203adaeacc39c7eac8b38a8b8b4d20975cad","reference":"e6ae203adaeacc39c7eac8b38a8b8b4d20975cad","shasum":""},"type":"yii2-extension","time":"2019-02-03T23:55:29+00:00","autoload":{"psr-4":{"skeeks\\cms\\marketplace\\":"src/"}},"extra":{"config-plugin":{"web":["src/config/common.php","src/config/web.php"],"console":["src/config/common.php"]}},"require":{"skeeks/cms":"^5.0.4 || dev-master","skeeks/cms-composer-update-plugin":"^1.0.0 || dev-master","yiisoft/yii2-httpclient":"^2","symfony/process":"~3.3.6"},"uid":2737112},"2.0.2.5":{"name":"skeeks/cms-marketplace","description":"Marketplace for SkeekS CMS","keywords":["framework","component","yii","marketplace","skeeks"],"homepage":"http://cms.skeeks.com/","version":"2.0.2.5","version_normalized":"2.0.2.5","license":["BSD-3-Clause"],"authors":[{"name":"Semenov Alexander","email":"semenov@skeeks.com"}],"source":{"type":"git","url":"https://github.com/skeeks-cms/cms-marketplace.git","reference":"e6ae203adaeacc39c7eac8b38a8b8b4d20975cad"},"dist":{"type":"zip","url":"https://api.github.com/repos/skeeks-cms/cms-marketplace/zipball/e6ae203adaeacc39c7eac8b38a8b8b4d20975cad","reference":"e6ae203adaeacc39c7eac8b38a8b8b4d20975cad","shasum":""},"type":"yii2-extension","time":"2019-02-03T23:55:29+00:00","autoload":{"psr-4":{"skeeks\\cms\\marketplace\\":"src/"}},"extra":{"config-plugin":{"web":["src/config/common.php","src/config/web.php"],"console":["src/config/common.php"]}},"require":{"skeeks/cms":"^5.0.4 || dev-master","skeeks/cms-composer-update-plugin":"^1.0.0 || dev-master","yiisoft/yii2-httpclient":"^2","symfony/process":"~3.3.6"},"uid":2739411},"dev-master":{"name":"skeeks/cms-marketplace","description":"Marketplace for SkeekS CMS","keywords":["framework","component","yii","marketplace","skeeks"],"homepage":"http://cms.skeeks.com/","version":"dev-master","version_normalized":"9999999-dev","license":["BSD-3-Clause"],"authors":[{"name":"Semenov Alexander","email":"semenov@skeeks.com"}],"source":{"type":"git","url":"https://github.com/skeeks-cms/cms-marketplace.git","reference":"e6ae203adaeacc39c7eac8b38a8b8b4d20975cad"},"dist":{"type":"zip","url":"https://api.github.com/repos/skeeks-cms/cms-marketplace/zipball/e6ae203adaeacc39c7eac8b38a8b8b4d20975cad","reference":"e6ae203adaeacc39c7eac8b38a8b8b4d20975cad","shasum":""},"type":"yii2-extension","time":"2019-02-03T23:55:29+00:00","autoload":{"psr-4":{"skeeks\\cms\\marketplace\\":"src/"}},"extra":{"config-plugin":{"web":["src/config/common.php","src/config/web.php"],"console":["src/config/common.php"]}},"require":{"symfony/process":"~3.3.6","skeeks/cms":"^5.0.4 || dev-master","skeeks/cms-composer-update-plugin":"^1.0.0 || dev-master","yiisoft/yii2-httpclient":"^2"},"uid":783674}}}}